libhttpcam/AuthDigest.py
libhttpcam/__init__.py
libhttpcam/foscam.py
libhttpcam/httpcam.py
libhttpcam/wansview.py
libhttpcam-0.1.4.dist-info/LICENSE
libhttpcam-0.1.4.dist-info/METADATA
libhttpcam-0.1.4.dist-info/WHEEL
libhttpcam-0.1.4.dist-info/top_level.txt
libhttpcam-0.1.4.dist-info/RECORD
