Metadata-Version: 2.1
Name: libhttpcam
Version: 0.1.4
Summary: Accessing webcams via REST API
Home-page: https://github.com/HelpfulScripts/libhttpcam
Author: Helpful Scripts
Author-email: helpfulscripts@gmail.com
License: UNKNOWN
Keywords: http camera foscam wansview
Platform: UNKNOWN
Classifier: Programming Language :: Python :: 3
Classifier: License :: OSI Approved :: MIT License
Classifier: Operating System :: OS Independent
Requires-Python: >=3.6
